{"is_source_file": true, "format": "TypeScript/TSX", "description": "This is a React functional component for a dashboard page in a Next.js application, defining the layout, sections, and UI components for the dashboard view.", "external_files": ["../../components/ui"], "external_methods": [], "published": ["DashboardPage"], "classes": [], "methods": [{"name": "DashboardPage", "description": "React functional component rendering the dashboard layout with statistics and recent activity."}], "calls": ["Link", "Button", "SectionHeader", "Stat", "Card"], "search-terms": ["next/link", "DashboardPage", "UI components", "React functional component", "dashboard layout", "recent activity"], "state": 2, "file_id": 15, "knowledge_revision": 124, "git_revision": "729694c9039ddc81fbb2b01b36be545790a4d51a", "revision_history": [{"43": ""}, {"48": ""}, {"49": ""}, {"89": "5906d238817b9f65fb437e6f1b2bd3d142041416"}, {"90": "5906d238817b9f65fb437e6f1b2bd3d142041416"}, {"96": "5906d238817b9f65fb437e6f1b2bd3d142041416"}, {"97": "5906d238817b9f65fb437e6f1b2bd3d142041416"}, {"99": "5906d238817b9f65fb437e6f1b2bd3d142041416"}, {"119": "729694c9039ddc81fbb2b01b36be545790a4d51a"}, {"124": "729694c9039ddc81fbb2b01b36be545790a4d51a"}], "ctags": [], "hash": "b95f622e3876aecdf967fc57f41bfc3e", "format-version": 4, "code-base-name": "unified_connector_frontend", "filename": "unified_connector_frontend/src/app/dashboard/page.tsx"}